jblib/__init__.py
jblib/color/__init__.py
jblib/color/hilight.py
jblib/conversion/__init__.py
jblib/conversion/convert_module.py
jblib/html_tools/__init__.py
jblib/html_tools/html_gen.py
jblib/logs/__init__.py
jblib/logs/logger.py
jblib/oslib/__init__.py
jblib/oslib/dir_libs.py
jblib/progress_bar/__init__.py
jblib/progress_bar/progress.py
jblib/time/__init__.py
jblib/time/time_tools.py
jblib-1.8.6.dist-info/LICENSE
jblib-1.8.6.dist-info/METADATA
jblib-1.8.6.dist-info/WHEEL
jblib-1.8.6.dist-info/top_level.txt
jblib-1.8.6.dist-info/RECORD
