Metadata-Version: 2.1
Name: jblib
Version: 1.8.6
Summary: JustBard's Python Utilities
Home-page: http://justbard.com
Author: Justin Bard
Author-email: JustinBard@gmail.com
Classifier: Programming Language :: Python :: 3
Classifier: License :: OSI Approved :: MIT License
Classifier: Operating System :: POSIX :: Linux
License-File: LICENSE
